{
  "posts": [
    {
      "title": "CSS偽元素after顯示字體圖                   ",
      "authorHTML": "<p><a href=\"https://blog.csdn.net/qq_41026588/article/details/105218950\" rel=\"noopener noreferrer\" target=\"_blank\">CSS伪元素after，显示字体图标 Font Awesome</a></p><p><br></p><pre class=\"ql-syntax\" spellcheck=\"false\">.shop_box li::before {\n  font-family: \"FontAwesome\";\n  content: '\\f0a9 ';\n  height: 20px;\n  width: 20px;\n  display: inline-block;\n}\n\n</pre><p><br></p>",
      "id": 1
    },
    {
      "title": "網站檢測工具",
      "authorHTML": "<ul><li><a href=\"https://developers.google.com/speed/pagespeed/insights/\" rel=\"noopener noreferrer\" target=\"_blank\">PageSpeed Insights</a></li><li><a href=\"https://www.webpagetest.org/\" rel=\"noopener noreferrer\" target=\"_blank\">webpagetest</a></li><li><a href=\"https://www.thinkwithgoogle.com/intl/zh-tw/feature/testmysite/\" rel=\"noopener noreferrer\" target=\"_blank\">think with google</a></li><li><a href=\"http://jigsaw.w3.org/css-validator/validator.html.en\" rel=\"noopener noreferrer\" target=\"_blank\">W3C CSS Validation Service</a></li><li><a href=\"http://validator.w3.org/\" rel=\"noopener noreferrer\" target=\"_blank\">W3C HTML Validation Service</a></li></ul>",
      "id": 2
    }
  ]
}